LICENSE
README.md
setup.py
ir_explain/__init__.py
ir_explain.egg-info/PKG-INFO
ir_explain.egg-info/SOURCES.txt
ir_explain.egg-info/dependency_links.txt
ir_explain.egg-info/requires.txt
ir_explain.egg-info/top_level.txt
ir_explain/datasets/__init__.py
ir_explain/datasets/dataIterBase.py
ir_explain/datasets/dataIterBert.py
ir_explain/datasets/dataIterDpr.py
ir_explain/datasets/dataIterDrmm.py
ir_explain/datasets/dataIterGlove.py
ir_explain/datasets/datasets.py
ir_explain/datasets/glove.py
ir_explain/datasets/trec.py
ir_explain/datasets/trecdl.py
ir_explain/eval/__init__.py
ir_explain/eval/metrics/__init__.py
ir_explain/eval/metrics/consistency.py
ir_explain/eval/metrics/correctness.py
ir_explain/explainers/__init__.py
ir_explain/explainers/base_explainer.py
ir_explain/explainers/listwise/__init__.py
ir_explain/explainers/listwise/base_listwise.py
ir_explain/explainers/listwise/bfs_explainer.py
ir_explain/explainers/listwise/greedy_explainer.py
ir_explain/explainers/listwise/intent_exs_explainer.py
ir_explain/explainers/listwise/multiplex_base.py
ir_explain/explainers/listwise/multiplex_explainer.py
ir_explain/explainers/listwise/simple_explainers.py
ir_explain/explainers/pairwise/__init__.py
ir_explain/explainers/pairwise/axioms.py
ir_explain/explainers/pairwise/explain_more.py
ir_explain/explainers/pointwise/__init__.py
ir_explain/explainers/pointwise/base_pointwise.py
ir_explain/explainers/pointwise/exs_explainer.py
ir_explain/explainers/pointwise/lirme_explainer.py
ir_explain/explainers/pointwise/lime/__init__.py
ir_explain/explainers/pointwise/lime/discretize.py
ir_explain/explainers/pointwise/lime/exceptions.py
ir_explain/explainers/pointwise/lime/explanation.py
ir_explain/explainers/pointwise/lime/lime_base.py
ir_explain/explainers/pointwise/lime/lime_image.py
ir_explain/explainers/pointwise/lime/lime_ranker.py
ir_explain/explainers/pointwise/lime/lime_tabular.py
ir_explain/explainers/pointwise/lime/lime_text.py
ir_explain/explainers/pointwise/lime/submodular_pick.py
ir_explain/explainers/pointwise/lime/utils/__init__.py
ir_explain/explainers/pointwise/lime/utils/generic_utils.py
